infoflow_robot/__about__.py
infoflow_robot/__init__.py
infoflow_robot/_robot.py
infoflow_robot/message.py
infoflow_robot-0.0.2.dist-info/METADATA
infoflow_robot-0.0.2.dist-info/WHEEL
infoflow_robot-0.0.2.dist-info/licenses/LICENSE.txt
infoflow_robot-0.0.2.dist-info/RECORD
