Metadata-Version: 2.4
Name: infoflow-robot
Version: 0.0.2
Summary: A Python SDK for baidu infoflow robot.
Project-URL: Documentation, https://github.com/jiwen-dev/infoflow-robot#readme
Project-URL: Issues, https://github.com/jiwen-dev/infoflow-robot/issues
Project-URL: Source, https://github.com/jiwen-dev/infoflow-robot
Author-email: jiwen <ji.wen@foxmail.com>
License-Expression: MIT
License-File: LICENSE.txt
Classifier: Development Status :: 4 - Beta
Classifier: Programming Language :: Python
Classifier: Programming Language :: Python :: 3.10
Classifier: Programming Language :: Python :: 3.11
Classifier: Programming Language :: Python :: 3.12
Classifier: Programming Language :: Python :: Implementation :: CPython
Classifier: Programming Language :: Python :: Implementation :: PyPy
Requires-Python: >=3.10
Requires-Dist: httpx>=0.28.1
Requires-Dist: pydantic>=2.10.6
